kerrgeopy/__init__.py
kerrgeopy/constants.py
kerrgeopy/frequencies.py
kerrgeopy/initial_conditions.py
kerrgeopy/orbit.py
kerrgeopy/plunge.py
kerrgeopy/spacetime.py
kerrgeopy/stable.py
kerrgeopy/units.py
kerrgeopy-0.9.3.dist-info/LICENSE
kerrgeopy-0.9.3.dist-info/METADATA
kerrgeopy-0.9.3.dist-info/WHEEL
kerrgeopy-0.9.3.dist-info/top_level.txt
kerrgeopy-0.9.3.dist-info/RECORD
