Metadata-Version: 2.1
Name: kerrgeopy
Version: 0.9.3
Summary: Library for computing stable and plunging geodesics in Kerr spacetime
Home-page: https://github.com/BlackHolePerturbationToolkit/KerrGeoPy
Author: Seyong Park
Classifier: Programming Language :: Python :: 3
Classifier: License :: OSI Approved :: MIT License
Classifier: Natural Language :: English
License-File: LICENSE
Requires-Dist: scipy >=1.8
Requires-Dist: numpy
Requires-Dist: matplotlib >=3.7
Requires-Dist: tqdm
